{"box_data": [{"position": {"minX": 232.19395446777344, "minY": 304.4117736816406, "maxX": 260.4697570800781, "maxY": 373.8078918457031}, "class_id": 7, "box_caption": "white-bishop 0.635", "scores": {"class_score": 0.6349973082542419}, "domain": "pixel"}, {"position": {"minX": 232.49822998046875, "minY": 306.0631103515625, "maxX": 261.85333251953125, "maxY": 372.00762939453125}, "class_id": 9, "box_caption": "white-knight 0.340", "scores": {"class_score": 0.33983004093170166}, "domain": "pixel"}, {"position": {"minX": 232.33987426757812, "minY": 305.8624267578125, "maxX": 260.7900085449219, "maxY": 372.269287109375}, "class_id": 11, "box_caption": "white-queen 0.270", "scores": {"class_score": 0.26965761184692383}, "domain": "pixel"}, {"position": {"minX": 233.1220703125, "minY": 303.94793701171875, "maxX": 261.28509521484375, "maxY": 373.8033447265625}, "class_id": 8, "box_caption": "white-king 0.022", "scores": {"class_score": 0.021666694432497025}, "domain": "pixel"}, {"position": {"minX": 232.77088928222656, "minY": 307.0594482421875, "maxX": 259.27734375, "maxY": 372.43243408203125}, "class_id": 12, "box_caption": "white-rook 0.012", "scores": {"class_score": 0.012419313192367554}, "domain": "pixel"}, {"position": {"minX": 231.88946533203125, "minY": 304.460693359375, "maxX": 260.98138427734375, "maxY": 373.0181884765625}, "class_id": 10, "box_caption": "white-pawn 0.009", "scores": {"class_score": 0.00915029738098383}, "domain": "pixel"}, {"position": {"minX": 232.3907012939453, "minY": 307.4976501464844, "maxX": 259.5914001464844, "maxY": 373.1412048339844}, "class_id": 3, "box_caption": "black-knight 0.009", "scores": {"class_score": 0.0087004154920578}, "domain": "pixel"}, {"position": {"minX": 232.77088928222656, "minY": 307.0594482421875, "maxX": 259.27734375, "maxY": 372.43243408203125}, "class_id": 1, "box_caption": "black-bishop 0.008", "scores": {"class_score": 0.008440115489065647}, "domain": "pixel"}, {"position": {"minX": 232.77088928222656, "minY": 307.0594482421875, "maxX": 259.27734375, "maxY": 372.43243408203125}, "class_id": 5, "box_caption": "black-queen 0.005", "scores": {"class_score": 0.005011445842683315}, "domain": "pixel"}, {"position": {"minX": 232.77088928222656, "minY": 307.0594482421875, "maxX": 259.27734375, "maxY": 372.43243408203125}, "class_id": 6, "box_caption": "black-rook 0.005", "scores": {"class_score": 0.004863500129431486}, "domain": "pixel"}, {"position": {"minX": 232.1337127685547, "minY": 305.3565673828125, "maxX": 260.7691345214844, "maxY": 373.4554443359375}, "class_id": 0, "box_caption": "bishop 0.005", "scores": {"class_score": 0.00468861311674118}, "domain": "pixel"}, {"position": {"minX": 239.68138122558594, "minY": 301.1460266113281, "maxX": 266.4599304199219, "maxY": 365.3732604980469}, "class_id": 11, "box_caption": "white-queen 0.003", "scores": {"class_score": 0.0025975091848522425}, "domain": "pixel"}, {"position": {"minX": 238.11810302734375, "minY": 300.0012512207031, "maxX": 266.5417785644531, "maxY": 364.4083557128906}, "class_id": 7, "box_caption": "white-bishop 0.002", "scores": {"class_score": 0.0023423812817782164}, "domain": "pixel"}, {"position": {"minX": 232.3480682373047, "minY": 306.10992431640625, "maxX": 261.32177734375, "maxY": 371.71392822265625}, "class_id": 4, "box_caption": "black-pawn 0.002", "scores": {"class_score": 0.0022148247808218002}, "domain": "pixel"}, {"position": {"minX": 238.11810302734375, "minY": 300.0012512207031, "maxX": 266.5417785644531, "maxY": 364.4083557128906}, "class_id": 9, "box_caption": "white-knight 0.002", "scores": {"class_score": 0.0016405879287049174}, "domain": "pixel"}, {"position": {"minX": 238.11810302734375, "minY": 300.0012512207031, "maxX": 266.5417785644531, "maxY": 364.4083557128906}, "class_id": 8, "box_caption": "white-king 0.001", "scores": {"class_score": 0.0013315959367901087}, "domain": "pixel"}, {"position": {"minX": 232.1337127685547, "minY": 305.3565673828125, "maxX": 260.7691345214844, "maxY": 373.4554443359375}, "class_id": 2, "box_caption": "black-king 0.001", "scores": {"class_score": 0.0010333806276321411}, "domain": "pixel"}], "class_labels": {"0": "bishop", "1": "black-bishop", "2": "black-king", "3": "black-knight", "4": "black-pawn", "5": "black-queen", "6": "black-rook", "7": "white-bishop", "8": "white-king", "9": "white-knight", "10": "white-pawn", "11": "white-queen", "12": "white-rook"}}